artkit/__init__.py
artkit/api.py
artkit/flow.py
artkit/py.typed
artkit/model/__init__.py
artkit/model/base/__init__.py
artkit/model/base/_adapter.py
artkit/model/base/_model.py
artkit/model/cache/__init__.py
artkit/model/cache/_cache.py
artkit/model/diffusion/__init__.py
artkit/model/diffusion/_cached.py
artkit/model/diffusion/base/__init__.py
artkit/model/diffusion/base/_diffusion.py
artkit/model/diffusion/base/_httpx_diffusion_connector.py
artkit/model/diffusion/bedrock/__init__.py
artkit/model/diffusion/bedrock/_titan.py
artkit/model/diffusion/bedrock/base/__init__.py
artkit/model/diffusion/bedrock/base/_base.py
artkit/model/diffusion/openai/__init__.py
artkit/model/diffusion/openai/_openai.py
artkit/model/llm/__init__.py
artkit/model/llm/_cached.py
artkit/model/llm/_gen2chat.py
artkit/model/llm/_generator.py
artkit/model/llm/_historized.py
artkit/model/llm/anthropic/__init__.py
artkit/model/llm/anthropic/_anthropic.py
artkit/model/llm/base/__init__.py
artkit/model/llm/base/_adapter.py
artkit/model/llm/base/_httpx_chat_connector.py
artkit/model/llm/base/_llm.py
artkit/model/llm/bedrock/__init__.py
artkit/model/llm/bedrock/_titan.py
artkit/model/llm/bedrock/base/__init__.py
artkit/model/llm/bedrock/base/_base.py
artkit/model/llm/gemini/__init__.py
artkit/model/llm/gemini/_gemini.py
artkit/model/llm/groq/__init__.py
artkit/model/llm/groq/_groq.py
artkit/model/llm/history/__init__.py
artkit/model/llm/history/_history.py
artkit/model/llm/history/_message.py
artkit/model/llm/huggingface/__init__.py
artkit/model/llm/huggingface/_huggingface.py
artkit/model/llm/huggingface/_huggingface_local.py
artkit/model/llm/huggingface/base/__init__.py
artkit/model/llm/huggingface/base/_base.py
artkit/model/llm/multi_turn/__init__.py
artkit/model/llm/multi_turn/_multi_turn.py
artkit/model/llm/openai/__init__.py
artkit/model/llm/openai/_openai.py
artkit/model/llm/util/__init__.py
artkit/model/llm/util/_json.py
artkit/model/llm/vertexai/__init__.py
artkit-1.0.8.dist-info/LICENSE
artkit-1.0.8.dist-info/WHEEL
artkit-1.0.8.dist-info/METADATA
artkit-1.0.8.dist-info/RECORD
