Metadata-Version: 2.1
Name: artkit
Version: 1.0.8
Summary: This section of the documentation provides detailed information
Home-page: https://github.com/BCG-X-Official/artkit
License: Apache Software License v2.0
Author: Boston Consulting Group (BCG)
Requires-Python: >=3.10,<4a
Requires-Dist: matplotlib               ~=3.6
Requires-Dist: pandas                   ~=2.1
Requires-Dist: gamma-pytools            ~=3.0
Requires-Dist: fluxus                   ~=1.0
Requires-Dist: typing_inspect           ~=0.7
Requires-Dist: anthropic                ~= 0.28 ; extra == "anthropic"
Requires-Dist: boto3                    ~= 1.34 ; extra == "boto3"
Requires-Dist: httpx                    ~= 0.27 ; extra == "boto3"
Requires-Dist: artkit[openai, groq, anthropic, google-generativeai, huggingface, boto3, google-cloud-aiplatform] ; extra == "dev"
Requires-Dist: python-dotenv            ~= 1.0 ; extra == "dev"
Requires-Dist: nbsphinx                 ~= 0.9 ; extra == "dev"
Requires-Dist: sphinx                   ~= 7.2 ; extra == "dev"
Requires-Dist: sphinx-autodoc-typehints ~= 1.25 ; extra == "dev"
Requires-Dist: pydata-sphinx-theme      ~= 0.15.1 ; extra == "dev"
Requires-Dist: packaging                ~= 24.1 ; extra == "dev"
Requires-Dist: ipywidgets               ~= 8.1 ; extra == "dev"
Requires-Dist: jupyterlab               ~= 4.2 ; extra == "dev"
Requires-Dist: notebook                 ~= 7.2 ; extra == "dev"
Requires-Dist: pytest                   ~= 8.2 ; extra == "dev"
Requires-Dist: pytest-asyncio           ~= 0.23 ; extra == "dev"
Requires-Dist: pytest-cov               ~= 5.0 ; extra == "dev"
Requires-Dist: pre-commit               ~= 3.7 ; extra == "dev"
Requires-Dist: moto                     ~= 5.0 ; extra == "dev"
Requires-Dist: google-cloud-aiplatform  ~= 1.62 ; extra == "google-cloud-aiplatform"
Requires-Dist: google-generativeai      ~= 0.6 ; extra == "google-generativeai"
Requires-Dist: groq                     ~= 0.9 ; extra == "groq"
Requires-Dist: aiohttp                  ~= 3.9 ; extra == "huggingface"
Requires-Dist: torch                    ~= 2.3 ; extra == "huggingface"
Requires-Dist: transformers             ~= 4.41 ; extra == "huggingface"
Requires-Dist: httpx                    ~= 0.27 ; extra == "huggingface"
Requires-Dist: openai                   ~= 1.34 ; extra == "openai"
Requires-Dist: pytest                   ~= 8.2 ; extra == "testing"
Requires-Dist: pytest-cov               ~= 5.0 ; extra == "testing"
Requires-Dist: pytest-asyncio           ~= 0.23 ; extra == "testing"
Project-URL: Documentation, https://bcg-x-official.github.io/artkit/
Project-URL: Repository, https://github.com/BCG-X-Official/artkit
Provides-Extra: anthropic
Provides-Extra: boto3
Provides-Extra: dev
Provides-Extra: google-cloud-aiplatform
Provides-Extra: google-generativeai
Provides-Extra: groq
Provides-Extra: huggingface
Provides-Extra: openai
Provides-Extra: testing
